intent/__init__.py
intent/autofill.py
intent/cli.py
intent/coverage.py
intent/merge.py
intent/requirements.py
pytest_intent-0.10.2.dist-info/METADATA
pytest_intent-0.10.2.dist-info/WHEEL
pytest_intent-0.10.2.dist-info/entry_points.txt
pytest_intent-0.10.2.dist-info/licenses/LICENSE-COMMERCIAL.md
pytest_intent-0.10.2.dist-info/RECORD
