Metadata-Version: 2.4
Name: pytest-intent
Version: 0.10.2
Summary: A pytest plugin for tracking requirement coverage.
License-Expression: Elastic-2.0
License-File: LICENSE-COMMERCIAL.md
Author: celestialorb
Author-email: chris.m.busby@gmail.com
Requires-Python: >=3.10,<3.14
Classifier: Programming Language :: Python :: 3
Classifier: Programming Language :: Python :: 3.10
Classifier: Programming Language :: Python :: 3.11
Classifier: Programming Language :: Python :: 3.12
Classifier: Programming Language :: Python :: 3.13
Requires-Dist: doorstop (>=3.0.2,<4.0.0)
Requires-Dist: pytest (>=9.0.0,<10.0.0)
Requires-Dist: pytest-harvest (>=1.10.5,<2.0.0)
Requires-Dist: rich-click (>=1.9.4,<2.0.0)
